tsbuilder/__init__.py
tsbuilder/architecture.py
tsbuilder/specs.py
tsbuilder/test_tsbuilder.py
tsbuilder-2.1.dist-info/Apache-2.0.txt
tsbuilder-2.1.dist-info/METADATA
tsbuilder-2.1.dist-info/WHEEL
tsbuilder-2.1.dist-info/top_level.txt
tsbuilder-2.1.dist-info/zip-safe
tsbuilder-2.1.dist-info/RECORD
