Metadata-Version: 2.1
Name: tsbuilder
Version: 2.1
Summary: Library for building test cases in the XML test format
Home-page: https://gitlab.com/sosy-lab/test-comp/test-format
Author: Dirk Beyer
Author-email: dirk.beyer@sosy-lab.org
License: Apache-2.0
Project-URL: Changelog, https://gitlab.com/sosy-lab/test-comp/test-format/-/blob/main/CHANGELOG.md
Project-URL: Issue Tracker, https://gitlab.com/sosy-lab/test-comp/test-format/-/issues
Keywords: testing,test suite,verification,XML,exchange,verification,Test-Comp
Platform: UNKNOWN
Classifier: Development Status :: 5 - Production/Stable
Classifier: Intended Audience :: Science/Research
Classifier: License :: OSI Approved :: Apache Software License
Classifier: Programming Language :: Python :: 3 :: Only
Classifier: Topic :: Software Development :: Testing
Requires-Python: >=3.5
License-File: LICENSES/Apache-2.0.txt
Requires-Dist: lxml (>=4.0.0)
